{
    "configurations": [
        {
            "name": "Linux",
            "includePath": [
                "${workspaceFolder}/**",
                "/lib/modules/5.0.0-37-generic/build/include",
                "/lib/modules/5.0.0-37-generic/build/arch/x86/include",
                "/lib/modules/5.0.0-37-generic/build/arch/x86/include/generated"
            ],
            "defines": [],
            "compilerPath": "/usr/bin/gcc",
            "cStandard": "c11",
            "cppStandard": "c++17",
            "intelliSenseMode": "gcc-x64"
        }
    ],
    "version": 4
}